{"stats":{"minecraft:custom":{"minecraft:time_since_rest":71901,"minecraft:sprint_one_cm":52651,"minecraft:damage_taken":240,"minecraft:walk_one_cm":122683,"minecraft:drop":43,"minecraft:talked_to_villager":2,"minecraft:interact_with_crafting_table":12,"minecraft:fly_one_cm":32524,"minecraft:open_barrel":1,"minecraft:open_chest":7,"minecraft:play_time":71901,"minecraft:interact_with_campfire":1,"minecraft:walk_under_water_one_cm":2283,"minecraft:boat_one_cm":275703,"minecraft:jump":361,"minecraft:walk_on_water_one_cm":1164,"minecraft:leave_game":4,"minecraft:time_since_death":71901,"minecraft:total_world_time":71901,"minecraft:climb_one_cm":1064,"minecraft:fall_one_cm":7252},"minecraft:dropped":{"minecraft:crossbow":1,"minecraft:oak_boat":1,"minecraft:oak_planks":1,"minecraft:lily_pad":40},"minecraft:picked_up":{"minecraft:dark_oak_sapling":1,"minecraft:charcoal":6,"minecraft:stick":6,"minecraft:crafting_table":2,"minecraft:potato":1,"minecraft:oak_log":7,"minecraft:lily_pad":40,"minecraft:spruce_sapling":12,"minecraft:spruce_log":40,"minecraft:dark_oak_log":14,"minecraft:dirt":7,"minecraft:pumpkin_pie":3,"minecraft:wheat_seeds":1,"minecraft:crossbow":1,"minecraft:rabbit":3,"minecraft:oak_planks":1,"minecraft:coal":31,"minecraft:cobblestone":364},"minecraft:used":{"minecraft:wooden_axe":65,"minecraft:bread":2,"minecraft:baked_potato":1,"minecraft:wooden_pickaxe":47,"minecraft:dirt":1,"minecraft:crafting_table":3,"minecraft:goat_horn":4,"minecraft:crossbow":2,"minecraft:oak_boat":4,"alexsmobs:animal_dictionary":3,"minecraft:potato":20,"justhammers:iron_hammer":46},"minecraft:crafted":{"minecraft:oak_planks":28,"justhammers:iron_hammer":1,"minecraft:crafting_table":1,"minecraft:stick":8,"minecraft:wooden_pickaxe":1,"minecraft:stone_pickaxe":1,"minecraft:wooden_axe":1,"minecraft:torch":4,"minecraft:dark_oak_planks":52,"minecraft:stone_axe":1},"minecraft:mined":{"minecraft:large_fern":2,"minecraft:dark_oak_log":19,"minecraft:spruce_log":40,"minecraft:mangrove_roots":1,"minecraft:crafting_table":2,"minecraft:grass":4,"minecraft:coal_ore":16,"minecraft:oak_log":7,"minecraft:grass_block":4,"minecraft:dirt":3,"minecraft:campfire":3,"minecraft:tall_grass":6,"minecraft:stone":25,"minecraft:fern":1},"minecraft:broken":{"minecraft:wooden_axe":1}},"DataVersion":3465}